setup.py
MongoOpCat/__init__.py
MongoOpCat.egg-info/PKG-INFO
MongoOpCat.egg-info/SOURCES.txt
MongoOpCat.egg-info/dependency_links.txt
MongoOpCat.egg-info/requires.txt
MongoOpCat.egg-info/top_level.txt
MongoOpCat/conf/Configuration.py
MongoOpCat/conf/MeChanism.py
MongoOpCat/conf/__init__.py
MongoOpCat/monitor/MonitorCat.py
MongoOpCat/monitor/__init__.py
MongoOpCat/sender/AbstractSender.py
MongoOpCat/sender/FSSenderCat.py
MongoOpCat/sender/StdOutSenderCat.py
MongoOpCat/sender/__init__.py
MongoOpCat/utils/BsonUtils.py
MongoOpCat/utils/__init__.py