Metadata-Version: 1.0
Name: MongoOpCat
Version: 0.0.3
Summary: a simple service which can monitor mongodb oplog
Home-page: UNKNOWN
Author: skyleft
Author-email: im@andy-cheung.me
License: MIT License
Keywords: mongodb,oplog
Platform: any
